dependencies_injection/__init__.py
dependencies_injection/exceptions.py
dependencies_injection/inject_param.py
dependencies_injection-1.0.dist-info/METADATA
dependencies_injection-1.0.dist-info/RECORD
dependencies_injection-1.0.dist-info/WHEEL
dependencies_injection-1.0.dist-info/top_level.txt
