Metadata-Version: 2.1
Name: dependencies-injection
Version: 1.0
Summary: A module to implement easily dependencies injection in python project.
Home-page: https://github.com/omauger/dependencies_injection
Author: Ophélie Mauger
License: MIT
Platform: UNKNOWN
Provides-Extra: ci
Requires-Dist: inject (==3.3.*)
Provides-Extra: ci
Requires-Dist: flake8; extra == 'ci'
Requires-Dist: coverage; extra == 'ci'
